moll/__init__.py
moll/metrics/__init__.py
moll/metrics/_metrics.py
moll/pick/__init__.py
moll/pick/_online_add.py
moll/pick/_online_picker.py
moll/small/__init__.py
moll/small/_mol.py
moll/typing.py
moll/utils/__init__.py
moll/utils/_data.py
moll/utils/_decorators.py
moll/utils/_utils.py
moll-0.1.12.dist-info/LICENSE
moll-0.1.12.dist-info/METADATA
moll-0.1.12.dist-info/WHEEL
moll-0.1.12.dist-info/RECORD
